neuradashhelp/__init__.py
neuradashhelp-0.0.2.dist-info/METADATA
neuradashhelp-0.0.2.dist-info/WHEEL
neuradashhelp-0.0.2.dist-info/top_level.txt
neuradashhelp-0.0.2.dist-info/RECORD
