Metadata-Version: 2.1
Name: neuradashhelp
Version: 0.0.2
Summary: Package fixing different troubleshootings
Home-page: https://github.com/peter777-cloud/neuradashhelp
Author: peter777
License: MIT
